integrates/__init__.py
integrates/auth/__init__.py
integrates/auth/api_key.py
integrates/auth/base.py
integrates/auth/basic.py
integrates/auth/bearer.py
integrates/auth/oauth2.py
integrates/core/__init__.py
integrates/core/client.py
integrates/core/exceptions.py
integrates/core/response.py
integrates/middleware/__init__.py
integrates/middleware/base.py
integrates/middleware/logging.py
integrates/middleware/rate_limit.py
integrates/middleware/retry.py
integrates/protocols/graphql/__init__.py
integrates/protocols/graphql/client.py
integrates/protocols/rest/__init__.py
integrates/protocols/rest/client.py
integrates/protocols/soap/__init__.py
integrates/protocols/soap/client.py
integrates/utils/__init__.py
integrates-0.1.1.dist-info/METADATA
integrates-0.1.1.dist-info/WHEEL
integrates-0.1.1.dist-info/top_level.txt
integrates-0.1.1.dist-info/RECORD
